__init__.py
drrank.py
drrank_distribution.py
drrank_loss.py
drrank_prior.py
drrank_utils.py
simul_pij.py
drrank-0.1.3.dist-info/LICENSE
drrank-0.1.3.dist-info/METADATA
drrank-0.1.3.dist-info/WHEEL
drrank-0.1.3.dist-info/top_level.txt
drrank-0.1.3.dist-info/RECORD
