Metadata-Version: 2.1
Name: drrank
Version: 0.1.3
Summary: Implement the Empirical Bayes ranking scheme developed in Kline, Rose, and Walters (2023)
Author-email: "Evan K. Rose" <ekrose@gmail.com>
Project-URL: Homepage, https://github.com/ekrose/drrank
Project-URL: Bug Tracker, https://github.com/ekrose/drrank/issues
Classifier: Programming Language :: Python :: 3
Classifier: License :: OSI Approved :: MIT License
Classifier: Operating System :: OS Independent
Requires-Python: >=3.8
License-File: LICENSE
Requires-Dist: numpy
Requires-Dist: pandas
Requires-Dist: scipy >=1.10.1
Requires-Dist: gurobipy <11.0.0,>=10.0.1
Requires-Dist: scikit-learn
Requires-Dist: tqdm
Requires-Dist: joblib >=1.1.0
Requires-Dist: patsy >=0.5.2
Requires-Dist: rpy2 >=3.5.13
Requires-Dist: matplotlib
Requires-Dist: seaborn
